ngxtop/__init__.py
ngxtop/config_parser.py
ngxtop/ngxtop.py
ngxtop/utils.py
ngxtop_ce-0.0.3a7.dist-info/LICENSE
ngxtop_ce-0.0.3a7.dist-info/METADATA
ngxtop_ce-0.0.3a7.dist-info/WHEEL
ngxtop_ce-0.0.3a7.dist-info/entry_points.txt
ngxtop_ce-0.0.3a7.dist-info/top_level.txt
ngxtop_ce-0.0.3a7.dist-info/RECORD
