Metadata-Version: 2.1
Name: ngxtop-ce
Version: 0.0.3a7
Summary: Real-time metrics for nginx server
Home-page: https://github.com/ngxtop/ngxtop
Author: Lucas Ramage
Author-email: ramage.lucas@protonmail.com
License: MIT
Keywords: cli monitoring nginx system
Platform: UNKNOWN
Classifier: Development Status :: 4 - Beta
Classifier: License :: OSI Approved :: MIT License
Classifier: Environment :: Console
Classifier: Intended Audience :: Developers
Classifier: Intended Audience :: System Administrators
Classifier: Programming Language :: Python :: 3
Classifier: Programming Language :: Python :: 3.2
Classifier: Programming Language :: Python :: 3.3
Classifier: Programming Language :: Python :: 3.7
Requires-Dist: docopt
Requires-Dist: tabulate
Requires-Dist: pyparsing
